<odoo>
  <data>
    <!-- explicit list view definition -->
    <!--
    <record model="ir.ui.view" id="hello_odoo.list">
      <field name="name">HelloOdoo list</field>
      <field name="model">hello_odoo.hello_odoo</field>
      <field name="arch" type="xml">
        <tree>
          <field name="name"/>
          <field name="value"/>
          <field name="value2"/>
        </tree>
      </field>
    </record>
    -->

    <!-- actions opening views on models -->
    <!--
    <record model="ir.actions.act_window" id="hello_odoo.action_window">
      <field name="name">HelloOdoo window</field>
      <field name="res_model">hello_odoo.hello_odoo</field>
      <field name="view_mode">tree,form</field>
    </record>
    -->

    <!-- server action to the one above -->
    <!--
    <record model="ir.actions.server" id="hello_odoo.action_server">
      <field name="name">HelloOdoo server</field>
      <field name="model_id" ref="model_hello_odoo_hello_odoo"/>
      <field name="code">
        action = {
          "type": "ir.actions.act_window",
          "view_mode": "tree,form",
          "res_model": self._name,
        }
      </field>
    </record>
    -->

    <!-- Top menu item -->
    <!--
    <menuitem name="HelloOdoo" id="hello_odoo.menu_root"/>
    -->
    <!-- menu categories -->
    <!--
    <menuitem name="Menu 1" id="hello_odoo.menu_1" parent="hello_odoo.menu_root"/>
    <menuitem name="Menu 2" id="hello_odoo.menu_2" parent="hello_odoo.menu_root"/>
    -->
    <!-- actions -->
    <!--
    <menuitem name="List" id="hello_odoo.menu_1_list" parent="hello_odoo.menu_1"
              action="hello_odoo.action_window"/>
    <menuitem name="Server to list" id="hello_odoo" parent="hello_odoo.menu_2"
              action="hello_odoo.action_server"/>
    -->
  </data>
</odoo>